{
  "candidate_pool_size": 39,
  "config": {
    "count": 10000,
    "coverage_bonuses": [
      0.0,
      0.01
    ],
    "expansion_complexity_penalties": [
      0.0,
      0.05
    ],
    "frequent_motif_metrics_csv_path": "outputs/v1/goal5_frequent_motif_metrics.csv",
    "frequent_motif_vocab_json_path": "outputs/v1/goal5_frequent_motif_vocab.json",
    "goal3_metrics_csv_path": "outputs/v1/dag_compression_metrics.csv",
    "input_jsonl_path": "outputs/v1/dag_compression_inputs.jsonl",
    "learned_vocab_json_path": "outputs/v1/goal5_learned_motif_vocab.json",
    "learned_vocab_sizes": [
      20,
      30
    ],
    "macro_graph_metrics_csv_path": "outputs/v1/goal5_macro_graph_metrics.csv",
    "max_depth": 4,
    "max_motif_nodes": 2,
    "metrics_csv_path": "outputs/v1/goal5_learned_motif_metrics.csv",
    "metrics_jsonl_path": "outputs/v1/goal5_learned_motif_metrics.jsonl",
    "min_motif_nodes": 1,
    "nontrivial_coverage_bonuses": [
      0.0,
      0.02
    ],
    "operator_set": [
      "add",
      "mul",
      "exp",
      "log"
    ],
    "seed": 0,
    "source_serialization": "srepr",
    "summary_json_path": "outputs/v1/goal5_learned_motif_summary.json",
    "symbol_names": [
      "x",
      "y"
    ],
    "train_fraction": 0.7,
    "train_log_json_path": "outputs/v1/goal5_learned_motif_train_log.json",
    "validation_fraction": 0.15,
    "vocab_complexity_penalties": [
      0.0,
      0.1
    ]
  },
  "hyperparameter_trials": [
    {
      "selected_motif_ids": [
        "pure_eml_dag_0000",
        "pure_eml_dag_0001",
        "pure_eml_dag_0002",
        "pure_eml_dag_0003",
        "pure_eml_dag_0004",
        "pure_eml_dag_0005",
        "pure_eml_dag_0006",
        "macro_graph_0000",
        "macro_graph_0002",
        "macro_graph_0001",
        "macro_graph_0003",
        "pure_eml_dag_0007",
        "macro_graph_0004",
        "macro_graph_0005",
        "macro_graph_0009",
        "macro_graph_0006",
        "macro_graph_0007",
        "macro_graph_0008",
        "macro_graph_0010",
        "macro_graph_0011"
      ],
      "train_objective": 616792.0,
      "validation_objective": 130307.0,
      "vocab_size": 20,
      "weights": {
        "coverage_bonus": 0.0,
        "expansion_complexity_penalty": 0.0,
        "nontrivial_coverage_bonus": 0.0,
        "vocab_complexity_penalty": 0.0
      }
    },
    {
      "selected_motif_ids": [
        "pure_eml_dag_0000",
        "pure_eml_dag_0001",
        "pure_eml_dag_0002",
        "pure_eml_dag_0003",
        "pure_eml_dag_0004",
        "pure_eml_dag_0005",
        "pure_eml_dag_0006",
        "macro_graph_0000",
        "macro_graph_0002",
        "macro_graph_0001",
        "macro_graph_0003",
        "pure_eml_dag_0007",
        "macro_graph_0004",
        "macro_graph_0005",
        "macro_graph_0009",
        "macro_graph_0006",
        "macro_graph_0007",
        "macro_graph_0008",
        "macro_graph_0010",
        "macro_graph_0011",
        "macro_graph_0012",
        "macro_graph_0013",
        "macro_graph_0014",
        "macro_graph_0015",
        "pure_eml_dag_0008",
        "macro_graph_0016",
        "macro_graph_0017",
        "macro_graph_0018",
        "macro_graph_0019",
        "macro_graph_0020"
      ],
      "train_objective": 633893.0,
      "validation_objective": 133967.0,
      "vocab_size": 30,
      "weights": {
        "coverage_bonus": 0.0,
        "expansion_complexity_penalty": 0.0,
        "nontrivial_coverage_bonus": 0.0,
        "vocab_complexity_penalty": 0.0
      }
    },
    {
      "selected_motif_ids": [
        "pure_eml_dag_0000",
        "pure_eml_dag_0001",
        "pure_eml_dag_0002",
        "pure_eml_dag_0003",
        "pure_eml_dag_0004",
        "pure_eml_dag_0005",
        "pure_eml_dag_0006",
        "macro_graph_0000",
        "macro_graph_0002",
        "macro_graph_0001",
        "macro_graph_0003",
        "pure_eml_dag_0007",
        "macro_graph_0004",
        "macro_graph_0005",
        "macro_graph_0009",
        "macro_graph_0006",
        "macro_graph_0007",
        "macro_graph_0008",
        "macro_graph_0010",
        "macro_graph_0011"
      ],
      "train_objective": 616787.35,
      "validation_objective": 130302.35,
      "vocab_size": 20,
      "weights": {
        "coverage_bonus": 0.0,
        "expansion_complexity_penalty": 0.05,
        "nontrivial_coverage_bonus": 0.0,
        "vocab_complexity_penalty": 0.0
      }
    },
    {
      "selected_motif_ids": [
        "pure_eml_dag_0000",
        "pure_eml_dag_0001",
        "pure_eml_dag_0002",
        "pure_eml_dag_0003",
        "pure_eml_dag_0004",
        "pure_eml_dag_0005",
        "pure_eml_dag_0006",
        "macro_graph_0000",
        "macro_graph_0002",
        "macro_graph_0001",
        "macro_graph_0003",
        "pure_eml_dag_0007",
        "macro_graph_0004",
        "macro_graph_0005",
        "macro_graph_0009",
        "macro_graph_0006",
        "macro_graph_0007",
        "macro_graph_0008",
        "macro_graph_0010",
        "macro_graph_0011",
        "macro_graph_0012",
        "macro_graph_0013",
        "macro_graph_0014",
        "macro_graph_0015",
        "pure_eml_dag_0008",
        "macro_graph_0016",
        "macro_graph_0017",
        "macro_graph_0018",
        "macro_graph_0019",
        "macro_graph_0020"
      ],
      "train_objective": 633886.65,
      "validation_objective": 133960.65,
      "vocab_size": 30,
      "weights": {
        "coverage_bonus": 0.0,
        "expansion_complexity_penalty": 0.05,
        "nontrivial_coverage_bonus": 0.0,
        "vocab_complexity_penalty": 0.0
      }
    },
    {
      "selected_motif_ids": [
        "pure_eml_dag_0000",
        "pure_eml_dag_0001",
        "pure_eml_dag_0002",
        "pure_eml_dag_0003",
        "pure_eml_dag_0004",
        "pure_eml_dag_0005",
        "pure_eml_dag_0006",
        "macro_graph_0000",
        "macro_graph_0002",
        "macro_graph_0001",
        "macro_graph_0003",
        "pure_eml_dag_0007",
        "macro_graph_0004",
        "macro_graph_0005",
        "macro_graph_0009",
        "macro_graph_0006",
        "macro_graph_0007",
        "macro_graph_0008",
        "macro_graph_0010",
        "macro_graph_0011"
      ],
      "train_objective": 616788.0,
      "validation_objective": 130303.0,
      "vocab_size": 20,
      "weights": {
        "coverage_bonus": 0.0,
        "expansion_complexity_penalty": 0.0,
        "nontrivial_coverage_bonus": 0.0,
        "vocab_complexity_penalty": 0.1
      }
    },
    {
      "selected_motif_ids": [
        "pure_eml_dag_0000",
        "pure_eml_dag_0001",
        "pure_eml_dag_0002",
        "pure_eml_dag_0003",
        "pure_eml_dag_0004",
        "pure_eml_dag_0005",
        "pure_eml_dag_0006",
        "macro_graph_0000",
        "macro_graph_0002",
        "macro_graph_0001",
        "macro_graph_0003",
        "pure_eml_dag_0007",
        "macro_graph_0004",
        "macro_graph_0005",
        "macro_graph_0009",
        "macro_graph_0006",
        "macro_graph_0007",
        "macro_graph_0008",
        "macro_graph_0010",
        "macro_graph_0011",
        "macro_graph_0012",
        "macro_graph_0013",
        "macro_graph_0014",
        "macro_graph_0015",
        "pure_eml_dag_0008",
        "macro_graph_0016",
        "macro_graph_0017",
        "macro_graph_0018",
        "macro_graph_0019",
        "macro_graph_0020"
      ],
      "train_objective": 633887.0,
      "validation_objective": 133961.0,
      "vocab_size": 30,
      "weights": {
        "coverage_bonus": 0.0,
        "expansion_complexity_penalty": 0.0,
        "nontrivial_coverage_bonus": 0.0,
        "vocab_complexity_penalty": 0.1
      }
    },
    {
      "selected_motif_ids": [
        "pure_eml_dag_0000",
        "pure_eml_dag_0001",
        "pure_eml_dag_0002",
        "pure_eml_dag_0003",
        "pure_eml_dag_0004",
        "pure_eml_dag_0005",
        "pure_eml_dag_0006",
        "macro_graph_0000",
        "macro_graph_0002",
        "macro_graph_0001",
        "macro_graph_0003",
        "pure_eml_dag_0007",
        "macro_graph_0004",
        "macro_graph_0005",
        "macro_graph_0009",
        "macro_graph_0006",
        "macro_graph_0007",
        "macro_graph_0008",
        "macro_graph_0010",
        "macro_graph_0011"
      ],
      "train_objective": 616783.35,
      "validation_objective": 130298.35,
      "vocab_size": 20,
      "weights": {
        "coverage_bonus": 0.0,
        "expansion_complexity_penalty": 0.05,
        "nontrivial_coverage_bonus": 0.0,
        "vocab_complexity_penalty": 0.1
      }
    },
    {
      "selected_motif_ids": [
        "pure_eml_dag_0000",
        "pure_eml_dag_0001",
        "pure_eml_dag_0002",
        "pure_eml_dag_0003",
        "pure_eml_dag_0004",
        "pure_eml_dag_0005",
        "pure_eml_dag_0006",
        "macro_graph_0000",
        "macro_graph_0002",
        "macro_graph_0001",
        "macro_graph_0003",
        "pure_eml_dag_0007",
        "macro_graph_0004",
        "macro_graph_0005",
        "macro_graph_0009",
        "macro_graph_0006",
        "macro_graph_0007",
        "macro_graph_0008",
        "macro_graph_0010",
        "macro_graph_0011",
        "macro_graph_0012",
        "macro_graph_0013",
        "macro_graph_0014",
        "macro_graph_0015",
        "pure_eml_dag_0008",
        "macro_graph_0016",
        "macro_graph_0017",
        "macro_graph_0018",
        "macro_graph_0019",
        "macro_graph_0020"
      ],
      "train_objective": 633880.65,
      "validation_objective": 133954.65,
      "vocab_size": 30,
      "weights": {
        "coverage_bonus": 0.0,
        "expansion_complexity_penalty": 0.05,
        "nontrivial_coverage_bonus": 0.0,
        "vocab_complexity_penalty": 0.1
      }
    },
    {
      "selected_motif_ids": [
        "pure_eml_dag_0000",
        "pure_eml_dag_0001",
        "pure_eml_dag_0002",
        "pure_eml_dag_0003",
        "pure_eml_dag_0004",
        "pure_eml_dag_0005",
        "pure_eml_dag_0006",
        "macro_graph_0000",
        "macro_graph_0002",
        "macro_graph_0001",
        "macro_graph_0003",
        "pure_eml_dag_0007",
        "macro_graph_0004",
        "macro_graph_0005",
        "macro_graph_0009",
        "macro_graph_0006",
        "macro_graph_0007",
        "macro_graph_0008",
        "macro_graph_0010",
        "macro_graph_0011"
      ],
      "train_objective": 625016.44,
      "validation_objective": 132104.44,
      "vocab_size": 20,
      "weights": {
        "coverage_bonus": 0.0,
        "expansion_complexity_penalty": 0.0,
        "nontrivial_coverage_bonus": 0.02,
        "vocab_complexity_penalty": 0.0
      }
    },
    {
      "selected_motif_ids": [
        "pure_eml_dag_0000",
        "pure_eml_dag_0001",
        "pure_eml_dag_0002",
        "pure_eml_dag_0003",
        "pure_eml_dag_0004",
        "pure_eml_dag_0005",
        "pure_eml_dag_0006",
        "macro_graph_0000",
        "macro_graph_0002",
        "macro_graph_0001",
        "macro_graph_0003",
        "pure_eml_dag_0007",
        "macro_graph_0004",
        "macro_graph_0005",
        "macro_graph_0009",
        "macro_graph_0006",
        "macro_graph_0007",
        "macro_graph_0008",
        "macro_graph_0010",
        "macro_graph_0011",
        "macro_graph_0012",
        "macro_graph_0013",
        "macro_graph_0014",
        "macro_graph_0015",
        "pure_eml_dag_0008",
        "macro_graph_0016",
        "macro_graph_0017",
        "macro_graph_0018",
        "macro_graph_0019",
        "macro_graph_0020"
      ],
      "train_objective": 642377.64,
      "validation_objective": 135821.84,
      "vocab_size": 30,
      "weights": {
        "coverage_bonus": 0.0,
        "expansion_complexity_penalty": 0.0,
        "nontrivial_coverage_bonus": 0.02,
        "vocab_complexity_penalty": 0.0
      }
    },
    {
      "selected_motif_ids": [
        "pure_eml_dag_0000",
        "pure_eml_dag_0001",
        "pure_eml_dag_0002",
        "pure_eml_dag_0003",
        "pure_eml_dag_0004",
        "pure_eml_dag_0005",
        "pure_eml_dag_0006",
        "macro_graph_0000",
        "macro_graph_0002",
        "macro_graph_0001",
        "macro_graph_0003",
        "pure_eml_dag_0007",
        "macro_graph_0004",
        "macro_graph_0005",
        "macro_graph_0009",
        "macro_graph_0006",
        "macro_graph_0007",
        "macro_graph_0008",
        "macro_graph_0010",
        "macro_graph_0011"
      ],
      "train_objective": 625011.79,
      "validation_objective": 132099.79,
      "vocab_size": 20,
      "weights": {
        "coverage_bonus": 0.0,
        "expansion_complexity_penalty": 0.05,
        "nontrivial_coverage_bonus": 0.02,
        "vocab_complexity_penalty": 0.0
      }
    },
    {
      "selected_motif_ids": [
        "pure_eml_dag_0000",
        "pure_eml_dag_0001",
        "pure_eml_dag_0002",
        "pure_eml_dag_0003",
        "pure_eml_dag_0004",
        "pure_eml_dag_0005",
        "pure_eml_dag_0006",
        "macro_graph_0000",
        "macro_graph_0002",
        "macro_graph_0001",
        "macro_graph_0003",
        "pure_eml_dag_0007",
        "macro_graph_0004",
        "macro_graph_0005",
        "macro_graph_0009",
        "macro_graph_0006",
        "macro_graph_0007",
        "macro_graph_0008",
        "macro_graph_0010",
        "macro_graph_0011",
        "macro_graph_0012",
        "macro_graph_0013",
        "macro_graph_0014",
        "macro_graph_0015",
        "pure_eml_dag_0008",
        "macro_graph_0016",
        "macro_graph_0017",
        "macro_graph_0018",
        "macro_graph_0019",
        "macro_graph_0020"
      ],
      "train_objective": 642371.29,
      "validation_objective": 135815.49,
      "vocab_size": 30,
      "weights": {
        "coverage_bonus": 0.0,
        "expansion_complexity_penalty": 0.05,
        "nontrivial_coverage_bonus": 0.02,
        "vocab_complexity_penalty": 0.0
      }
    },
    {
      "selected_motif_ids": [
        "pure_eml_dag_0000",
        "pure_eml_dag_0001",
        "pure_eml_dag_0002",
        "pure_eml_dag_0003",
        "pure_eml_dag_0004",
        "pure_eml_dag_0005",
        "pure_eml_dag_0006",
        "macro_graph_0000",
        "macro_graph_0002",
        "macro_graph_0001",
        "macro_graph_0003",
        "pure_eml_dag_0007",
        "macro_graph_0004",
        "macro_graph_0005",
        "macro_graph_0009",
        "macro_graph_0006",
        "macro_graph_0007",
        "macro_graph_0008",
        "macro_graph_0010",
        "macro_graph_0011"
      ],
      "train_objective": 625012.44,
      "validation_objective": 132100.44,
      "vocab_size": 20,
      "weights": {
        "coverage_bonus": 0.0,
        "expansion_complexity_penalty": 0.0,
        "nontrivial_coverage_bonus": 0.02,
        "vocab_complexity_penalty": 0.1
      }
    },
    {
      "selected_motif_ids": [
        "pure_eml_dag_0000",
        "pure_eml_dag_0001",
        "pure_eml_dag_0002",
        "pure_eml_dag_0003",
        "pure_eml_dag_0004",
        "pure_eml_dag_0005",
        "pure_eml_dag_0006",
        "macro_graph_0000",
        "macro_graph_0002",
        "macro_graph_0001",
        "macro_graph_0003",
        "pure_eml_dag_0007",
        "macro_graph_0004",
        "macro_graph_0005",
        "macro_graph_0009",
        "macro_graph_0006",
        "macro_graph_0007",
        "macro_graph_0008",
        "macro_graph_0010",
        "macro_graph_0011",
        "macro_graph_0012",
        "macro_graph_0013",
        "macro_graph_0014",
        "macro_graph_0015",
        "pure_eml_dag_0008",
        "macro_graph_0016",
        "macro_graph_0017",
        "macro_graph_0018",
        "macro_graph_0019",
        "macro_graph_0020"
      ],
      "train_objective": 642371.64,
      "validation_objective": 135815.84,
      "vocab_size": 30,
      "weights": {
        "coverage_bonus": 0.0,
        "expansion_complexity_penalty": 0.0,
        "nontrivial_coverage_bonus": 0.02,
        "vocab_complexity_penalty": 0.1
      }
    },
    {
      "selected_motif_ids": [
        "pure_eml_dag_0000",
        "pure_eml_dag_0001",
        "pure_eml_dag_0002",
        "pure_eml_dag_0003",
        "pure_eml_dag_0004",
        "pure_eml_dag_0005",
        "pure_eml_dag_0006",
        "macro_graph_0000",
        "macro_graph_0002",
        "macro_graph_0001",
        "macro_graph_0003",
        "pure_eml_dag_0007",
        "macro_graph_0004",
        "macro_graph_0005",
        "macro_graph_0009",
        "macro_graph_0006",
        "macro_graph_0007",
        "macro_graph_0008",
        "macro_graph_0010",
        "macro_graph_0011"
      ],
      "train_objective": 625007.7899999999,
      "validation_objective": 132095.79,
      "vocab_size": 20,
      "weights": {
        "coverage_bonus": 0.0,
        "expansion_complexity_penalty": 0.05,
        "nontrivial_coverage_bonus": 0.02,
        "vocab_complexity_penalty": 0.1
      }
    },
    {
      "selected_motif_ids": [
        "pure_eml_dag_0000",
        "pure_eml_dag_0001",
        "pure_eml_dag_0002",
        "pure_eml_dag_0003",
        "pure_eml_dag_0004",
        "pure_eml_dag_0005",
        "pure_eml_dag_0006",
        "macro_graph_0000",
        "macro_graph_0002",
        "macro_graph_0001",
        "macro_graph_0003",
        "pure_eml_dag_0007",
        "macro_graph_0004",
        "macro_graph_0005",
        "macro_graph_0009",
        "macro_graph_0006",
        "macro_graph_0007",
        "macro_graph_0008",
        "macro_graph_0010",
        "macro_graph_0011",
        "macro_graph_0012",
        "macro_graph_0013",
        "macro_graph_0014",
        "macro_graph_0015",
        "pure_eml_dag_0008",
        "macro_graph_0016",
        "macro_graph_0017",
        "macro_graph_0018",
        "macro_graph_0019",
        "macro_graph_0020"
      ],
      "train_objective": 642365.2899999999,
      "validation_objective": 135809.49,
      "vocab_size": 30,
      "weights": {
        "coverage_bonus": 0.0,
        "expansion_complexity_penalty": 0.05,
        "nontrivial_coverage_bonus": 0.02,
        "vocab_complexity_penalty": 0.1
      }
    },
    {
      "selected_motif_ids": [
        "pure_eml_dag_0000",
        "pure_eml_dag_0001",
        "pure_eml_dag_0002",
        "pure_eml_dag_0003",
        "pure_eml_dag_0004",
        "pure_eml_dag_0005",
        "pure_eml_dag_0006",
        "macro_graph_0000",
        "macro_graph_0002",
        "macro_graph_0001",
        "macro_graph_0003",
        "pure_eml_dag_0007",
        "macro_graph_0004",
        "macro_graph_0005",
        "macro_graph_0009",
        "macro_graph_0006",
        "macro_graph_0007",
        "macro_graph_0008",
        "macro_graph_0010",
        "macro_graph_0011"
      ],
      "train_objective": 629127.84,
      "validation_objective": 132913.14,
      "vocab_size": 20,
      "weights": {
        "coverage_bonus": 0.01,
        "expansion_complexity_penalty": 0.0,
        "nontrivial_coverage_bonus": 0.0,
        "vocab_complexity_penalty": 0.0
      }
    },
    {
      "selected_motif_ids": [
        "pure_eml_dag_0000",
        "pure_eml_dag_0001",
        "pure_eml_dag_0002",
        "pure_eml_dag_0003",
        "pure_eml_dag_0004",
        "pure_eml_dag_0005",
        "pure_eml_dag_0006",
        "macro_graph_0000",
        "macro_graph_0002",
        "macro_graph_0001",
        "macro_graph_0003",
        "pure_eml_dag_0007",
        "macro_graph_0004",
        "macro_graph_0005",
        "macro_graph_0009",
        "macro_graph_0006",
        "macro_graph_0007",
        "macro_graph_0008",
        "macro_graph_0010",
        "macro_graph_0011",
        "macro_graph_0012",
        "macro_graph_0013",
        "macro_graph_0014",
        "macro_graph_0015",
        "pure_eml_dag_0008",
        "macro_graph_0016",
        "macro_graph_0017",
        "macro_graph_0018",
        "macro_graph_0019",
        "macro_graph_0020"
      ],
      "train_objective": 646570.86,
      "validation_objective": 136646.34,
      "vocab_size": 30,
      "weights": {
        "coverage_bonus": 0.01,
        "expansion_complexity_penalty": 0.0,
        "nontrivial_coverage_bonus": 0.0,
        "vocab_complexity_penalty": 0.0
      }
    },
    {
      "selected_motif_ids": [
        "pure_eml_dag_0000",
        "pure_eml_dag_0001",
        "pure_eml_dag_0002",
        "pure_eml_dag_0003",
        "pure_eml_dag_0004",
        "pure_eml_dag_0005",
        "pure_eml_dag_0006",
        "macro_graph_0000",
        "macro_graph_0002",
        "macro_graph_0001",
        "macro_graph_0003",
        "pure_eml_dag_0007",
        "macro_graph_0004",
        "macro_graph_0005",
        "macro_graph_0009",
        "macro_graph_0006",
        "macro_graph_0007",
        "macro_graph_0008",
        "macro_graph_0010",
        "macro_graph_0011"
      ],
      "train_objective": 629123.1900000001,
      "validation_objective": 132908.49,
      "vocab_size": 20,
      "weights": {
        "coverage_bonus": 0.01,
        "expansion_complexity_penalty": 0.05,
        "nontrivial_coverage_bonus": 0.0,
        "vocab_complexity_penalty": 0.0
      }
    },
    {
      "selected_motif_ids": [
        "pure_eml_dag_0000",
        "pure_eml_dag_0001",
        "pure_eml_dag_0002",
        "pure_eml_dag_0003",
        "pure_eml_dag_0004",
        "pure_eml_dag_0005",
        "pure_eml_dag_0006",
        "macro_graph_0000",
        "macro_graph_0002",
        "macro_graph_0001",
        "macro_graph_0003",
        "pure_eml_dag_0007",
        "macro_graph_0004",
        "macro_graph_0005",
        "macro_graph_0009",
        "macro_graph_0006",
        "macro_graph_0007",
        "macro_graph_0008",
        "macro_graph_0010",
        "macro_graph_0011",
        "macro_graph_0012",
        "macro_graph_0013",
        "macro_graph_0014",
        "macro_graph_0015",
        "pure_eml_dag_0008",
        "macro_graph_0016",
        "macro_graph_0017",
        "macro_graph_0018",
        "macro_graph_0019",
        "macro_graph_0020"
      ],
      "train_objective": 646564.51,
      "validation_objective": 136639.99,
      "vocab_size": 30,
      "weights": {
        "coverage_bonus": 0.01,
        "expansion_complexity_penalty": 0.05,
        "nontrivial_coverage_bonus": 0.0,
        "vocab_complexity_penalty": 0.0
      }
    },
    {
      "selected_motif_ids": [
        "pure_eml_dag_0000",
        "pure_eml_dag_0001",
        "pure_eml_dag_0002",
        "pure_eml_dag_0003",
        "pure_eml_dag_0004",
        "pure_eml_dag_0005",
        "pure_eml_dag_0006",
        "macro_graph_0000",
        "macro_graph_0002",
        "macro_graph_0001",
        "macro_graph_0003",
        "pure_eml_dag_0007",
        "macro_graph_0004",
        "macro_graph_0005",
        "macro_graph_0009",
        "macro_graph_0006",
        "macro_graph_0007",
        "macro_graph_0008",
        "macro_graph_0010",
        "macro_graph_0011"
      ],
      "train_objective": 629123.84,
      "validation_objective": 132909.14,
      "vocab_size": 20,
      "weights": {
        "coverage_bonus": 0.01,
        "expansion_complexity_penalty": 0.0,
        "nontrivial_coverage_bonus": 0.0,
        "vocab_complexity_penalty": 0.1
      }
    },
    {
      "selected_motif_ids": [
        "pure_eml_dag_0000",
        "pure_eml_dag_0001",
        "pure_eml_dag_0002",
        "pure_eml_dag_0003",
        "pure_eml_dag_0004",
        "pure_eml_dag_0005",
        "pure_eml_dag_0006",
        "macro_graph_0000",
        "macro_graph_0002",
        "macro_graph_0001",
        "macro_graph_0003",
        "pure_eml_dag_0007",
        "macro_graph_0004",
        "macro_graph_0005",
        "macro_graph_0009",
        "macro_graph_0006",
        "macro_graph_0007",
        "macro_graph_0008",
        "macro_graph_0010",
        "macro_graph_0011",
        "macro_graph_0012",
        "macro_graph_0013",
        "macro_graph_0014",
        "macro_graph_0015",
        "pure_eml_dag_0008",
        "macro_graph_0016",
        "macro_graph_0017",
        "macro_graph_0018",
        "macro_graph_0019",
        "macro_graph_0020"
      ],
      "train_objective": 646564.86,
      "validation_objective": 136640.34,
      "vocab_size": 30,
      "weights": {
        "coverage_bonus": 0.01,
        "expansion_complexity_penalty": 0.0,
        "nontrivial_coverage_bonus": 0.0,
        "vocab_complexity_penalty": 0.1
      }
    },
    {
      "selected_motif_ids": [
        "pure_eml_dag_0000",
        "pure_eml_dag_0001",
        "pure_eml_dag_0002",
        "pure_eml_dag_0003",
        "pure_eml_dag_0004",
        "pure_eml_dag_0005",
        "pure_eml_dag_0006",
        "macro_graph_0000",
        "macro_graph_0002",
        "macro_graph_0001",
        "macro_graph_0003",
        "pure_eml_dag_0007",
        "macro_graph_0004",
        "macro_graph_0005",
        "macro_graph_0009",
        "macro_graph_0006",
        "macro_graph_0007",
        "macro_graph_0008",
        "macro_graph_0010",
        "macro_graph_0011"
      ],
      "train_objective": 629119.1900000001,
      "validation_objective": 132904.49000000002,
      "vocab_size": 20,
      "weights": {
        "coverage_bonus": 0.01,
        "expansion_complexity_penalty": 0.05,
        "nontrivial_coverage_bonus": 0.0,
        "vocab_complexity_penalty": 0.1
      }
    },
    {
      "selected_motif_ids": [
        "pure_eml_dag_0000",
        "pure_eml_dag_0001",
        "pure_eml_dag_0002",
        "pure_eml_dag_0003",
        "pure_eml_dag_0004",
        "pure_eml_dag_0005",
        "pure_eml_dag_0006",
        "macro_graph_0000",
        "macro_graph_0002",
        "macro_graph_0001",
        "macro_graph_0003",
        "pure_eml_dag_0007",
        "macro_graph_0004",
        "macro_graph_0005",
        "macro_graph_0009",
        "macro_graph_0006",
        "macro_graph_0007",
        "macro_graph_0008",
        "macro_graph_0010",
        "macro_graph_0011",
        "macro_graph_0012",
        "macro_graph_0013",
        "macro_graph_0014",
        "macro_graph_0015",
        "pure_eml_dag_0008",
        "macro_graph_0016",
        "macro_graph_0017",
        "macro_graph_0018",
        "macro_graph_0019",
        "macro_graph_0020"
      ],
      "train_objective": 646558.51,
      "validation_objective": 136633.99000000002,
      "vocab_size": 30,
      "weights": {
        "coverage_bonus": 0.01,
        "expansion_complexity_penalty": 0.05,
        "nontrivial_coverage_bonus": 0.0,
        "vocab_complexity_penalty": 0.1
      }
    },
    {
      "selected_motif_ids": [
        "pure_eml_dag_0000",
        "pure_eml_dag_0001",
        "pure_eml_dag_0002",
        "pure_eml_dag_0003",
        "pure_eml_dag_0004",
        "pure_eml_dag_0005",
        "pure_eml_dag_0006",
        "macro_graph_0000",
        "macro_graph_0002",
        "macro_graph_0001",
        "macro_graph_0003",
        "pure_eml_dag_0007",
        "macro_graph_0004",
        "macro_graph_0005",
        "macro_graph_0009",
        "macro_graph_0006",
        "macro_graph_0007",
        "macro_graph_0008",
        "macro_graph_0010",
        "macro_graph_0011"
      ],
      "train_objective": 637352.28,
      "validation_objective": 134710.58000000002,
      "vocab_size": 20,
      "weights": {
        "coverage_bonus": 0.01,
        "expansion_complexity_penalty": 0.0,
        "nontrivial_coverage_bonus": 0.02,
        "vocab_complexity_penalty": 0.0
      }
    },
    {
      "selected_motif_ids": [
        "pure_eml_dag_0000",
        "pure_eml_dag_0001",
        "pure_eml_dag_0002",
        "pure_eml_dag_0003",
        "pure_eml_dag_0004",
        "pure_eml_dag_0005",
        "pure_eml_dag_0006",
        "macro_graph_0000",
        "macro_graph_0002",
        "macro_graph_0001",
        "macro_graph_0003",
        "pure_eml_dag_0007",
        "macro_graph_0004",
        "macro_graph_0005",
        "macro_graph_0009",
        "macro_graph_0006",
        "macro_graph_0007",
        "macro_graph_0008",
        "macro_graph_0010",
        "macro_graph_0011",
        "macro_graph_0012",
        "macro_graph_0013",
        "macro_graph_0014",
        "macro_graph_0015",
        "pure_eml_dag_0008",
        "macro_graph_0016",
        "macro_graph_0017",
        "macro_graph_0018",
        "macro_graph_0019",
        "macro_graph_0020"
      ],
      "train_objective": 655055.5,
      "validation_objective": 138501.18,
      "vocab_size": 30,
      "weights": {
        "coverage_bonus": 0.01,
        "expansion_complexity_penalty": 0.0,
        "nontrivial_coverage_bonus": 0.02,
        "vocab_complexity_penalty": 0.0
      }
    },
    {
      "selected_motif_ids": [
        "pure_eml_dag_0000",
        "pure_eml_dag_0001",
        "pure_eml_dag_0002",
        "pure_eml_dag_0003",
        "pure_eml_dag_0004",
        "pure_eml_dag_0005",
        "pure_eml_dag_0006",
        "macro_graph_0000",
        "macro_graph_0002",
        "macro_graph_0001",
        "macro_graph_0003",
        "pure_eml_dag_0007",
        "macro_graph_0004",
        "macro_graph_0005",
        "macro_graph_0009",
        "macro_graph_0006",
        "macro_graph_0007",
        "macro_graph_0008",
        "macro_graph_0010",
        "macro_graph_0011"
      ],
      "train_objective": 637347.63,
      "validation_objective": 134705.93,
      "vocab_size": 20,
      "weights": {
        "coverage_bonus": 0.01,
        "expansion_complexity_penalty": 0.05,
        "nontrivial_coverage_bonus": 0.02,
        "vocab_complexity_penalty": 0.0
      }
    },
    {
      "selected_motif_ids": [
        "pure_eml_dag_0000",
        "pure_eml_dag_0001",
        "pure_eml_dag_0002",
        "pure_eml_dag_0003",
        "pure_eml_dag_0004",
        "pure_eml_dag_0005",
        "pure_eml_dag_0006",
        "macro_graph_0000",
        "macro_graph_0002",
        "macro_graph_0001",
        "macro_graph_0003",
        "pure_eml_dag_0007",
        "macro_graph_0004",
        "macro_graph_0005",
        "macro_graph_0009",
        "macro_graph_0006",
        "macro_graph_0007",
        "macro_graph_0008",
        "macro_graph_0010",
        "macro_graph_0011",
        "macro_graph_0012",
        "macro_graph_0013",
        "macro_graph_0014",
        "macro_graph_0015",
        "pure_eml_dag_0008",
        "macro_graph_0016",
        "macro_graph_0017",
        "macro_graph_0018",
        "macro_graph_0019",
        "macro_graph_0020"
      ],
      "train_objective": 655049.15,
      "validation_objective": 138494.83000000002,
      "vocab_size": 30,
      "weights": {
        "coverage_bonus": 0.01,
        "expansion_complexity_penalty": 0.05,
        "nontrivial_coverage_bonus": 0.02,
        "vocab_complexity_penalty": 0.0
      }
    },
    {
      "selected_motif_ids": [
        "pure_eml_dag_0000",
        "pure_eml_dag_0001",
        "pure_eml_dag_0002",
        "pure_eml_dag_0003",
        "pure_eml_dag_0004",
        "pure_eml_dag_0005",
        "pure_eml_dag_0006",
        "macro_graph_0000",
        "macro_graph_0002",
        "macro_graph_0001",
        "macro_graph_0003",
        "pure_eml_dag_0007",
        "macro_graph_0004",
        "macro_graph_0005",
        "macro_graph_0009",
        "macro_graph_0006",
        "macro_graph_0007",
        "macro_graph_0008",
        "macro_graph_0010",
        "macro_graph_0011"
      ],
      "train_objective": 637348.28,
      "validation_objective": 134706.58000000002,
      "vocab_size": 20,
      "weights": {
        "coverage_bonus": 0.01,
        "expansion_complexity_penalty": 0.0,
        "nontrivial_coverage_bonus": 0.02,
        "vocab_complexity_penalty": 0.1
      }
    },
    {
      "selected_motif_ids": [
        "pure_eml_dag_0000",
        "pure_eml_dag_0001",
        "pure_eml_dag_0002",
        "pure_eml_dag_0003",
        "pure_eml_dag_0004",
        "pure_eml_dag_0005",
        "pure_eml_dag_0006",
        "macro_graph_0000",
        "macro_graph_0002",
        "macro_graph_0001",
        "macro_graph_0003",
        "pure_eml_dag_0007",
        "macro_graph_0004",
        "macro_graph_0005",
        "macro_graph_0009",
        "macro_graph_0006",
        "macro_graph_0007",
        "macro_graph_0008",
        "macro_graph_0010",
        "macro_graph_0011",
        "macro_graph_0012",
        "macro_graph_0013",
        "macro_graph_0014",
        "macro_graph_0015",
        "pure_eml_dag_0008",
        "macro_graph_0016",
        "macro_graph_0017",
        "macro_graph_0018",
        "macro_graph_0019",
        "macro_graph_0020"
      ],
      "train_objective": 655049.5,
      "validation_objective": 138495.18,
      "vocab_size": 30,
      "weights": {
        "coverage_bonus": 0.01,
        "expansion_complexity_penalty": 0.0,
        "nontrivial_coverage_bonus": 0.02,
        "vocab_complexity_penalty": 0.1
      }
    },
    {
      "selected_motif_ids": [
        "pure_eml_dag_0000",
        "pure_eml_dag_0001",
        "pure_eml_dag_0002",
        "pure_eml_dag_0003",
        "pure_eml_dag_0004",
        "pure_eml_dag_0005",
        "pure_eml_dag_0006",
        "macro_graph_0000",
        "macro_graph_0002",
        "macro_graph_0001",
        "macro_graph_0003",
        "pure_eml_dag_0007",
        "macro_graph_0004",
        "macro_graph_0005",
        "macro_graph_0009",
        "macro_graph_0006",
        "macro_graph_0007",
        "macro_graph_0008",
        "macro_graph_0010",
        "macro_graph_0011"
      ],
      "train_objective": 637343.63,
      "validation_objective": 134701.93,
      "vocab_size": 20,
      "weights": {
        "coverage_bonus": 0.01,
        "expansion_complexity_penalty": 0.05,
        "nontrivial_coverage_bonus": 0.02,
        "vocab_complexity_penalty": 0.1
      }
    },
    {
      "selected_motif_ids": [
        "pure_eml_dag_0000",
        "pure_eml_dag_0001",
        "pure_eml_dag_0002",
        "pure_eml_dag_0003",
        "pure_eml_dag_0004",
        "pure_eml_dag_0005",
        "pure_eml_dag_0006",
        "macro_graph_0000",
        "macro_graph_0002",
        "macro_graph_0001",
        "macro_graph_0003",
        "pure_eml_dag_0007",
        "macro_graph_0004",
        "macro_graph_0005",
        "macro_graph_0009",
        "macro_graph_0006",
        "macro_graph_0007",
        "macro_graph_0008",
        "macro_graph_0010",
        "macro_graph_0011",
        "macro_graph_0012",
        "macro_graph_0013",
        "macro_graph_0014",
        "macro_graph_0015",
        "pure_eml_dag_0008",
        "macro_graph_0016",
        "macro_graph_0017",
        "macro_graph_0018",
        "macro_graph_0019",
        "macro_graph_0020"
      ],
      "train_objective": 655043.15,
      "validation_objective": 138488.83000000002,
      "vocab_size": 30,
      "weights": {
        "coverage_bonus": 0.01,
        "expansion_complexity_penalty": 0.05,
        "nontrivial_coverage_bonus": 0.02,
        "vocab_complexity_penalty": 0.1
      }
    }
  ],
  "model_type": "deterministic_linear_motif_scorer",
  "random_motif_ids": [
    "macro_graph_0000",
    "macro_graph_0001",
    "macro_graph_0003",
    "macro_graph_0004",
    "macro_graph_0005",
    "macro_graph_0006",
    "macro_graph_0007",
    "macro_graph_0008",
    "macro_graph_0009",
    "macro_graph_0010",
    "macro_graph_0011",
    "macro_graph_0012",
    "macro_graph_0013",
    "macro_graph_0014",
    "macro_graph_0015",
    "macro_graph_0017",
    "macro_graph_0018",
    "macro_graph_0020",
    "macro_graph_0021",
    "macro_graph_0022",
    "macro_graph_0023",
    "macro_graph_0027",
    "macro_graph_0028",
    "macro_graph_0029",
    "pure_eml_dag_0003",
    "pure_eml_dag_0004",
    "pure_eml_dag_0005",
    "pure_eml_dag_0006",
    "pure_eml_dag_0007",
    "pure_eml_dag_0008"
  ],
  "selected_motif_ids": [
    "pure_eml_dag_0000",
    "pure_eml_dag_0001",
    "pure_eml_dag_0002",
    "pure_eml_dag_0003",
    "pure_eml_dag_0004",
    "pure_eml_dag_0005",
    "pure_eml_dag_0006",
    "macro_graph_0000",
    "macro_graph_0002",
    "macro_graph_0001",
    "macro_graph_0003",
    "pure_eml_dag_0007",
    "macro_graph_0004",
    "macro_graph_0005",
    "macro_graph_0009",
    "macro_graph_0006",
    "macro_graph_0007",
    "macro_graph_0008",
    "macro_graph_0010",
    "macro_graph_0011",
    "macro_graph_0012",
    "macro_graph_0013",
    "macro_graph_0014",
    "macro_graph_0015",
    "pure_eml_dag_0008",
    "macro_graph_0016",
    "macro_graph_0017",
    "macro_graph_0018",
    "macro_graph_0019",
    "macro_graph_0020"
  ],
  "selected_vocab_size": 30,
  "selected_weights": {
    "coverage_bonus": 0.01,
    "expansion_complexity_penalty": 0.0,
    "nontrivial_coverage_bonus": 0.02,
    "vocab_complexity_penalty": 0.0
  },
  "selection_policy": "train scores choose motifs; validation objective chooses hyperparameters",
  "split_counts": {
    "test": 1488,
    "train": 7021,
    "validation": 1491
  },
  "test_set_used_for_selection": false,
  "trained_final_reasoning_gnn": false
}
